[
  {
    "id": 1,
    "name": "ABC BATERAI JAM"
  },
  {
    "id": 2,
    "name": "ABC BATERAI REMOT"
  },
  {
    "id": 3,
    "name": "ABC BATERAI REMOT HITAM"
  },
  {
    "id": 4,
    "name": "ABC BOTOL CHOCOMALT"
  },
  {
    "id": 5,
    "name": "ABC GULA AREN"
  },
  {
    "id": 6,
    "name": "ABC KECAP 250G"
  },
  {
    "id": 7,
    "name": "ABC KECAP 600G"
  },
  {
    "id": 8,
    "name": "ABC KECAP 62G B3G1"
  },
  {
    "id": 9,
    "name": "ABC KECAP 685G"
  },
  {
    "id": 10,
    "name": "ABC KECAP ASIN BOTOL 131ML"
  },
  {
    "id": 11,
    "name": "ABC KECAP BOTOL 130ML"
  },
  {
    "id": 12,
    "name": "ABC KECAP BOTOL 275ML"
  },
  {
    "id": 13,
    "name": "ABC KECAP BOTOL PEDAS 275ML"
  },
  {
    "id": 14,
    "name": "ABC KECAP HITAM 62G B2G1"
  },
  {
    "id": 15,
    "name": "ABC KECAP R"
  },
  {
    "id": 16,
    "name": "ABC MIE AYAM BAWANG"
  },
  {
    "id": 17,
    "name": "ABC MIX"
  },
  {
    "id": 18,
    "name": "ABC MOCA"
  },
  {
    "id": 19,
    "name": "ABC PLUS"
  },
  {
    "id": 20,
    "name": "ABC SAMBAL 65G ASLI"
  },
  {
    "id": 21,
    "name": "ABC SAMBAL 65G EXTRA PEDAS"
  },
  {
    "id": 22,
    "name": "ABC SAMBAL ASLI NUSANTARA R"
  },
  {
    "id": 23,
    "name": "ABC SAMBAL ASLI STIK"
  },
  {
    "id": 24,
    "name": "ABC SAMBAL BOTOL 130ML ASLI"
  },
  {
    "id": 25,
    "name": "ABC SAMBAL BOTOL 130ML EXTRA PEDAS"
  },
  {
    "id": 26,
    "name": "ABC SAMBAL BOTOL 130ML EXTREME PEDAS"
  },
  {
    "id": 27,
    "name": "ABC SAMBAL BOTOL 270ML ASLI"
  },
  {
    "id": 28,
    "name": "ABC SAMBAL BOTOL 270ML EXTRA PEDAS"
  },
  {
    "id": 29,
    "name": "ABC SAMBAL BOTOL 270ML EXTREME PEDAS"
  },
  {
    "id": 30,
    "name": "ABC SAMBAL EXTRA PEDAS R"
  },
  {
    "id": 31,
    "name": "ABC SAMBAL EXTRA PEDAS STIK"
  },
  {
    "id": 32,
    "name": "ABC SAMBAL TERASI R"
  },
  {
    "id": 33,
    "name": "ABC SAMBAL TOMAT BOTOL 130ML"
  },
  {
    "id": 34,
    "name": "ABC SAMBAL TOMAT BOTOL 270ML"
  },
  {
    "id": 35,
    "name": "ABC SAMBAL TOMAT STIK"
  },
  {
    "id": 36,
    "name": "ABC SIRUP SQUASH JERUK"
  },
  {
    "id": 37,
    "name": "ABC SUSU"
  },
  {
    "id": 38,
    "name": "ABC TERASI UDANG PAK"
  },
  {
    "id": 39,
    "name": "ABON 100G"
  },
  {
    "id": 40,
    "name": "ABON 32"
  },
  {
    "id": 41,
    "name": "ABON 50G"
  },
  {
    "id": 42,
    "name": "ABON CUP"
  },
  {
    "id": 43,
    "name": "ACI"
  },
  {
    "id": 44,
    "name": "ADEM SARI CHINGKU BOTOL"
  },
  {
    "id": 45,
    "name": "ADEM SARI CHINGKU KALENG"
  },
  {
    "id": 46,
    "name": "ADEM SARI SAC"
  },
  {
    "id": 47,
    "name": "AGARIA COKLAT"
  },
  {
    "id": 48,
    "name": "AGUNG 1000"
  },
  {
    "id": 49,
    "name": "AGUNG 2000"
  },
  {
    "id": 50,
    "name": "AGUNG CAIR 450ML"
  },
  {
    "id": 1,
    "name": "ABC BATERAI JAM"
  },
  {
    "id": 2,
    "name": "ABC BATERAI REMOT"
  },
  {
    "id": 3,
    "name": "ABC BATERAI REMOT HITAM"
  },
  {
    "id": 4,
    "name": "ABC BOTOL CHOCOMALT"
  },
  {
    "id": 5,
    "name": "ABC GULA AREN"
  },
  {
    "id": 6,
    "name": "ABC KECAP 250G"
  },
  {
    "id": 7,
    "name": "ABC KECAP 600G"
  },
  {
    "id": 8,
    "name": "ABC KECAP 62G B3G1"
  },
  {
    "id": 9,
    "name": "ABC KECAP 685G"
  },
  {
    "id": 10,
    "name": "ABC KECAP ASIN BOTOL 131ML"
  },
  {
    "id": 11,
    "name": "ABC KECAP BOTOL 130ML"
  },
  {
    "id": 12,
    "name": "ABC KECAP BOTOL 275ML"
  },
  {
    "id": 13,
    "name": "ABC KECAP BOTOL PEDAS 275ML"
  },
  {
    "id": 14,
    "name": "ABC KECAP HITAM 62G B2G1"
  },
  {
    "id": 15,
    "name": "ABC KECAP R"
  },
  {
    "id": 16,
    "name": "ABC MIE AYAM BAWANG"
  },
  {
    "id": 17,
    "name": "ABC MIX"
  },
  {
    "id": 18,
    "name": "ABC MOCA"
  },
  {
    "id": 19,
    "name": "ABC PLUS"
  },
  {
    "id": 20,
    "name": "ABC SAMBAL 65G ASLI"
  },
  {
    "id": 21,
    "name": "ABC SAMBAL 65G EXTRA PEDAS"
  },
  {
    "id": 22,
    "name": "ABC SAMBAL ASLI NUSANTARA R"
  },
  {
    "id": 23,
    "name": "ABC SAMBAL ASLI STIK"
  },
  {
    "id": 24,
    "name": "ABC SAMBAL BOTOL 130ML ASLI"
  },
  {
    "id": 25,
    "name": "ABC SAMBAL BOTOL 130ML EXTRA PEDAS"
  },
  {
    "id": 26,
    "name": "ABC SAMBAL BOTOL 130ML EXTREME PEDAS"
  },
  {
    "id": 27,
    "name": "ABC SAMBAL BOTOL 270ML ASLI"
  },
  {
    "id": 28,
    "name": "ABC SAMBAL BOTOL 270ML EXTRA PEDAS"
  },
  {
    "id": 29,
    "name": "ABC SAMBAL BOTOL 270ML EXTREME PEDAS"
  },
  {
    "id": 30,
    "name": "ABC SAMBAL EXTRA PEDAS R"
  },
  {
    "id": 31,
    "name": "ABC SAMBAL EXTRA PEDAS STIK"
  },
  {
    "id": 32,
    "name": "ABC SAMBAL TERASI R"
  },
  {
    "id": 33,
    "name": "ABC SAMBAL TOMAT BOTOL 130ML"
  },
  {
    "id": 34,
    "name": "ABC SAMBAL TOMAT BOTOL 270ML"
  },
  {
    "id": 35,
    "name": "ABC SAMBAL TOMAT STIK"
  },
  {
    "id": 36,
    "name": "ABC SIRUP SQUASH JERUK"
  },
  {
    "id": 37,
    "name": "ABC SUSU"
  },
  {
    "id": 38,
    "name": "ABC TERASI UDANG PAK"
  },
  {
    "id": 39,
    "name": "ABON 100G"
  },
  {
    "id": 40,
    "name": "ABON 32"
  },
  {
    "id": 41,
    "name": "ABON 50G"
  },
  {
    "id": 42,
    "name": "ABON CUP"
  },
  {
    "id": 43,
    "name": "ACI"
  },
  {
    "id": 44,
    "name": "ADEM SARI CHINGKU BOTOL"
  },
  {
    "id": 45,
    "name": "ADEM SARI CHINGKU KALENG"
  },
  {
    "id": 46,
    "name": "ADEM SARI SAC"
  },
  {
    "id": 47,
    "name": "AGARIA COKLAT"
  },
  {
    "id": 48,
    "name": "AGUNG 1000"
  },
  {
    "id": 49,
    "name": "AGUNG 2000"
  },
  {
    "id": 50,
    "name": "AGUNG CAIR 450ML"
  },
  {
    "id": 1,
    "name": "ABC BATERAI JAM"
  },
  {
    "id": 2,
    "name": "ABC BATERAI REMOT"
  },
  {
    "id": 3,
    "name": "ABC BATERAI REMOT HITAM"
  },
  {
    "id": 4,
    "name": "ABC BOTOL CHOCOMALT"
  },
  {
    "id": 5,
    "name": "ABC GULA AREN"
  },
  {
    "id": 6,
    "name": "ABC KECAP 250G"
  },
  {
    "id": 7,
    "name": "ABC KECAP 600G"
  },
  {
    "id": 8,
    "name": "ABC KECAP 62G B3G1"
  },
  {
    "id": 9,
    "name": "ABC KECAP 685G"
  },
  {
    "id": 10,
    "name": "ABC KECAP ASIN BOTOL 131ML"
  },
  {
    "id": 11,
    "name": "ABC KECAP BOTOL 130ML"
  },
  {
    "id": 12,
    "name": "ABC KECAP BOTOL 275ML"
  },
  {
    "id": 13,
    "name": "ABC KECAP BOTOL PEDAS 275ML"
  },
  {
    "id": 14,
    "name": "ABC KECAP HITAM 62G B2G1"
  },
  {
    "id": 15,
    "name": "ABC KECAP R"
  },
  {
    "id": 16,
    "name": "ABC MIE AYAM BAWANG"
  },
  {
    "id": 17,
    "name": "ABC MIX"
  },
  {
    "id": 18,
    "name": "ABC MOCA"
  },
  {
    "id": 19,
    "name": "ABC PLUS"
  },
  {
    "id": 20,
    "name": "ABC SAMBAL 65G ASLI"
  },
  {
    "id": 21,
    "name": "ABC SAMBAL 65G EXTRA PEDAS"
  },
  {
    "id": 22,
    "name": "ABC SAMBAL ASLI NUSANTARA R"
  },
  {
    "id": 23,
    "name": "ABC SAMBAL ASLI STIK"
  },
  {
    "id": 24,
    "name": "ABC SAMBAL BOTOL 130ML ASLI"
  },
  {
    "id": 25,
    "name": "ABC SAMBAL BOTOL 130ML EXTRA PEDAS"
  },
  {
    "id": 26,
    "name": "ABC SAMBAL BOTOL 130ML EXTREME PEDAS"
  },
  {
    "id": 27,
    "name": "ABC SAMBAL BOTOL 270ML ASLI"
  },
  {
    "id": 28,
    "name": "ABC SAMBAL BOTOL 270ML EXTRA PEDAS"
  },
  {
    "id": 29,
    "name": "ABC SAMBAL BOTOL 270ML EXTREME PEDAS"
  },
  {
    "id": 30,
    "name": "ABC SAMBAL EXTRA PEDAS R"
  },
  {
    "id": 31,
    "name": "ABC SAMBAL EXTRA PEDAS STIK"
  },
  {
    "id": 32,
    "name": "ABC SAMBAL TERASI R"
  },
  {
    "id": 33,
    "name": "ABC SAMBAL TOMAT BOTOL 130ML"
  },
  {
    "id": 34,
    "name": "ABC SAMBAL TOMAT BOTOL 270ML"
  },
  {
    "id": 35,
    "name": "ABC SAMBAL TOMAT STIK"
  },
  {
    "id": 36,
    "name": "ABC SIRUP SQUASH JERUK"
  },
  {
    "id": 37,
    "name": "ABC SUSU"
  },
  {
    "id": 38,
    "name": "ABC TERASI UDANG PAK"
  },
  {
    "id": 39,
    "name": "ABON 100G"
  },
  {
    "id": 40,
    "name": "ABON 32"
  },
  {
    "id": 41,
    "name": "ABON 50G"
  },
  {
    "id": 42,
    "name": "ABON CUP"
  },
  {
    "id": 43,
    "name": "ACI"
  },
  {
    "id": 44,
    "name": "ADEM SARI CHINGKU BOTOL"
  },
  {
    "id": 45,
    "name": "ADEM SARI CHINGKU KALENG"
  },
  {
    "id": 46,
    "name": "ADEM SARI SAC"
  },
  {
    "id": 47,
    "name": "AGARIA COKLAT"
  },
  {
    "id": 48,
    "name": "AGUNG 1000"
  },
  {
    "id": 49,
    "name": "AGUNG 2000"
  },
  {
    "id": 50,
    "name": "AGUNG CAIR 450ML"
  },
  {
    "id": 1,
    "name": "ABC BATERAI JAM"
  },
  {
    "id": 2,
    "name": "ABC BATERAI REMOT"
  },
  {
    "id": 3,
    "name": "ABC BATERAI REMOT HITAM"
  },
  {
    "id": 4,
    "name": "ABC BOTOL CHOCOMALT"
  },
  {
    "id": 5,
    "name": "ABC GULA AREN"
  },
  {
    "id": 6,
    "name": "ABC KECAP 250G"
  },
  {
    "id": 7,
    "name": "ABC KECAP 600G"
  },
  {
    "id": 8,
    "name": "ABC KECAP 62G B3G1"
  },
  {
    "id": 9,
    "name": "ABC KECAP 685G"
  },
  {
    "id": 10,
    "name": "ABC KECAP ASIN BOTOL 131ML"
  },
  {
    "id": 11,
    "name": "ABC KECAP BOTOL 130ML"
  },
  {
    "id": 12,
    "name": "ABC KECAP BOTOL 275ML"
  },
  {
    "id": 13,
    "name": "ABC KECAP BOTOL PEDAS 275ML"
  },
  {
    "id": 14,
    "name": "ABC KECAP HITAM 62G B2G1"
  },
  {
    "id": 15,
    "name": "ABC KECAP R"
  },
  {
    "id": 16,
    "name": "ABC MIE AYAM BAWANG"
  },
  {
    "id": 17,
    "name": "ABC MIX"
  },
  {
    "id": 18,
    "name": "ABC MOCA"
  },
  {
    "id": 19,
    "name": "ABC PLUS"
  },
  {
    "id": 20,
    "name": "ABC SAMBAL 65G ASLI"
  },
  {
    "id": 21,
    "name": "ABC SAMBAL 65G EXTRA PEDAS"
  },
  {
    "id": 22,
    "name": "ABC SAMBAL ASLI NUSANTARA R"
  },
  {
    "id": 23,
    "name": "ABC SAMBAL ASLI STIK"
  },
  {
    "id": 24,
    "name": "ABC SAMBAL BOTOL 130ML ASLI"
  },
  {
    "id": 25,
    "name": "ABC SAMBAL BOTOL 130ML EXTRA PEDAS"
  },
  {
    "id": 26,
    "name": "ABC SAMBAL BOTOL 130ML EXTREME PEDAS"
  },
  {
    "id": 27,
    "name": "ABC SAMBAL BOTOL 270ML ASLI"
  },
  {
    "id": 28,
    "name": "ABC SAMBAL BOTOL 270ML EXTRA PEDAS"
  },
  {
    "id": 29,
    "name": "ABC SAMBAL BOTOL 270ML EXTREME PEDAS"
  },
  {
    "id": 30,
    "name": "ABC SAMBAL EXTRA PEDAS R"
  },
  {
    "id": 31,
    "name": "ABC SAMBAL EXTRA PEDAS STIK"
  },
  {
    "id": 32,
    "name": "ABC SAMBAL TERASI R"
  },
  {
    "id": 33,
    "name": "ABC SAMBAL TOMAT BOTOL 130ML"
  },
  {
    "id": 34,
    "name": "ABC SAMBAL TOMAT BOTOL 270ML"
  },
  {
    "id": 35,
    "name": "ABC SAMBAL TOMAT STIK"
  },
  {
    "id": 36,
    "name": "ABC SIRUP SQUASH JERUK"
  },
  {
    "id": 37,
    "name": "ABC SUSU"
  },
  {
    "id": 38,
    "name": "ABC TERASI UDANG PAK"
  },
  {
    "id": 39,
    "name": "ABON 100G"
  },
  {
    "id": 40,
    "name": "ABON 32"
  },
  {
    "id": 41,
    "name": "ABON 50G"
  },
  {
    "id": 42,
    "name": "ABON CUP"
  },
  {
    "id": 43,
    "name": "ACI"
  },
  {
    "id": 44,
    "name": "ADEM SARI CHINGKU BOTOL"
  },
  {
    "id": 45,
    "name": "ADEM SARI CHINGKU KALENG"
  },
  {
    "id": 46,
    "name": "ADEM SARI SAC"
  },
  {
    "id": 47,
    "name": "AGARIA COKLAT"
  },
  {
    "id": 48,
    "name": "AGUNG 1000"
  },
  {
    "id": 49,
    "name": "AGUNG 2000"
  },
  {
    "id": 50,
    "name": "AGUNG CAIR 450ML"
  }
]